{"tags": ["train", "finished"], "description": "", "objects": [{"description": "", "bitmap": null, "tags": [], "classTitle": "Wheat-grain-damaged", "points": {"exterior": [[314.0, 91.0], [306.0, 103.0], [306.0, 111.0], [311.0, 115.0], [311.0, 170.0], [316.0, 170.0], [319.0, 175.0], [333.0, 175.0], [363.0, 167.0], [367.0, 152.0], [360.0, 135.0], [336.0, 103.0], [327.0, 99.0], [323.0, 91.0]], "interior": []}}, {"description": "", "bitmap": null, "tags": [], "classTitle": "Wheat-grain", "points": {"exterior": [[276.0, 330.0], [276.0, 358.0], [288.0, 372.0], [296.0, 389.0], [309.0, 399.0], [337.0, 411.0], [373.0, 436.0], [400.0, 442.0], [451.0, 440.0], [476.0, 433.0], [475.0, 415.0], [455.0, 369.0], [383.0, 322.0], [345.0, 310.0], [320.0, 308.0]], "interior": []}}, {"description": "", "bitmap": null, "tags": [], "classTitle": "Wheat-grain", "points": {"exterior": [[251.0, 397.0], [248.0, 434.0], [255.0, 463.0], [276.0, 492.0], [299.0, 511.0], [428.0, 511.0], [424.0, 494.0], [413.0, 472.0], [392.0, 451.0], [348.0, 419.0], [306.0, 397.0], [291.0, 394.0]], "interior": []}}, {"description": "", "bitmap": null, "tags": [], "classTitle": "Wheat-grain", "points": {"exterior": [[170.0, 358.0], [152.0, 386.0], [151.0, 423.0], [170.0, 486.0], [184.0, 511.0], [271.0, 511.0], [272.0, 487.0], [261.0, 475.0], [253.0, 456.0], [248.0, 423.0], [236.0, 396.0], [215.0, 367.0], [194.0, 360.0]], "interior": []}}, {"description": "", "bitmap": null, "tags": [], "classTitle": "Wheat-grain-damaged", "points": {"exterior": [[29.0, 408.0], [21.0, 408.0], [0.0, 422.0], [0.0, 500.0], [25.0, 484.0], [35.0, 469.0], [45.0, 443.0], [41.0, 424.0], [29.0, 412.0]], "interior": []}}, {"description": "", "bitmap": null, "tags": [], "classTitle": "Wheat-grain", "points": {"exterior": [[76.0, 493.0], [68.0, 480.0], [61.0, 476.0], [58.0, 467.0], [50.0, 467.0], [31.0, 479.0], [26.0, 479.0], [13.0, 494.0], [3.0, 498.0], [0.0, 502.0], [0.0, 511.0], [76.0, 511.0]], "interior": []}}, {"description": "", "bitmap": null, "tags": [], "classTitle": "Wheat-grain", "points": {"exterior": [[113.0, 418.0], [90.0, 444.0], [78.0, 511.0], [180.0, 511.0], [155.0, 447.0], [139.0, 429.0]], "interior": []}}, {"description": "", "bitmap": null, "tags": [], "classTitle": "Wheat-grain", "points": {"exterior": [[378.0, 0.0], [417.0, 42.0], [449.0, 64.0], [472.0, 74.0], [511.0, 74.0], [511.0, 0.0]], "interior": []}}, {"description": "", "bitmap": null, "tags": [], "classTitle": "Wheat-grain", "points": {"exterior": [[269.0, 0.0], [300.0, 48.0], [312.0, 77.0], [347.0, 107.0], [360.0, 110.0], [366.0, 108.0], [377.0, 67.0], [377.0, 49.0], [365.0, 1.0]], "interior": []}}, {"description": "", "bitmap": null, "tags": [], "classTitle": "Wheat-grain", "points": {"exterior": [[401.0, 51.0], [389.0, 58.0], [384.0, 65.0], [374.0, 98.0], [375.0, 134.0], [383.0, 165.0], [393.0, 187.0], [413.0, 214.0], [415.0, 221.0], [433.0, 229.0], [454.0, 244.0], [465.0, 244.0], [480.0, 217.0], [487.0, 182.0], [486.0, 147.0], [474.0, 105.0], [465.0, 88.0], [451.0, 72.0], [423.0, 55.0]], "interior": []}}, {"description": "", "bitmap": null, "tags": [], "classTitle": "Wheat-grain", "points": {"exterior": [[266.0, 20.0], [256.0, 36.0], [240.0, 47.0], [228.0, 50.0], [222.0, 56.0], [213.0, 89.0], [212.0, 121.0], [217.0, 168.0], [228.0, 202.0], [249.0, 223.0], [267.0, 232.0], [292.0, 207.0], [300.0, 189.0], [309.0, 144.0], [309.0, 112.0], [300.0, 65.0], [290.0, 47.0], [272.0, 31.0]], "interior": []}}, {"description": "", "bitmap": null, "tags": [], "classTitle": "Wheat-grain", "points": {"exterior": [[417.0, 308.0], [416.0, 315.0], [425.0, 339.0], [442.0, 354.0], [460.0, 364.0], [511.0, 377.0], [510.0, 282.0], [459.0, 283.0], [436.0, 293.0]], "interior": []}}, {"description": "", "bitmap": null, "tags": [], "classTitle": "Wheat-grain", "points": {"exterior": [[21.0, 193.0], [16.0, 216.0], [19.0, 239.0], [36.0, 265.0], [70.0, 297.0], [113.0, 325.0], [131.0, 332.0], [164.0, 333.0], [189.0, 328.0], [190.0, 301.0], [185.0, 274.0], [170.0, 251.0], [123.0, 206.0], [92.0, 187.0], [73.0, 180.0], [55.0, 179.0]], "interior": []}}, {"description": "", "bitmap": null, "tags": [], "classTitle": "Wheat-grain", "points": {"exterior": [[70.0, 69.0], [59.0, 84.0], [59.0, 107.0], [69.0, 142.0], [107.0, 187.0], [159.0, 221.0], [174.0, 224.0], [207.0, 221.0], [212.0, 216.0], [214.0, 202.0], [213.0, 179.0], [209.0, 166.0], [197.0, 145.0], [166.0, 107.0], [139.0, 81.0], [121.0, 71.0], [91.0, 64.0], [77.0, 65.0]], "interior": []}}, {"description": "", "bitmap": null, "tags": [], "classTitle": "Wheat-grain", "points": {"exterior": [[0.0, 0.0], [0.0, 57.0], [38.0, 79.0], [44.0, 79.0], [59.0, 69.0], [69.0, 55.0], [77.0, 30.0], [76.0, 0.0]], "interior": []}}, {"description": "", "bitmap": null, "tags": [], "classTitle": "Wheat-grain", "points": {"exterior": [[51.0, 117.0], [30.0, 109.0], [0.0, 106.0], [0.0, 189.0], [39.0, 174.0], [64.0, 149.0], [57.0, 138.0], [59.0, 129.0]], "interior": []}}, {"description": "", "bitmap": null, "tags": [], "classTitle": "Wheat-grain", "points": {"exterior": [[83.0, 0.0], [97.0, 28.0], [132.0, 68.0], [154.0, 77.0], [154.0, 82.0], [164.0, 91.0], [181.0, 91.0], [184.0, 82.0], [177.0, 43.0], [172.0, 31.0], [162.0, 22.0], [150.0, 0.0]], "interior": []}}, {"description": "", "bitmap": null, "tags": [], "classTitle": "Wheat-grain", "points": {"exterior": [[161.0, 0.0], [172.0, 20.0], [192.0, 37.0], [209.0, 44.0], [240.0, 45.0], [246.0, 42.0], [255.0, 31.0], [261.0, 0.0]], "interior": []}}, {"description": "", "bitmap": null, "tags": [], "classTitle": "Wheat-grain", "points": {"exterior": [[511.0, 446.0], [500.0, 449.0], [475.0, 474.0], [465.0, 493.0], [460.0, 511.0], [511.0, 511.0]], "interior": []}}], "size": {"height": 512, "width": 512}}