{"tags": ["finished", "val"], "description": "", "objects": [{"description": "", "bitmap": null, "tags": [], "classTitle": "Agrostemma", "points": {"exterior": [[234.0, 359.0], [222.0, 363.0], [219.0, 368.0], [211.0, 369.0], [196.0, 384.0], [189.0, 384.0], [184.0, 396.0], [171.0, 411.0], [174.0, 415.0], [175.0, 428.0], [193.0, 451.0], [210.0, 460.0], [225.0, 460.0], [242.0, 468.0], [250.0, 457.0], [258.0, 457.0], [256.0, 447.0], [262.0, 438.0], [262.0, 409.0], [256.0, 391.0], [255.0, 380.0], [259.0, 379.0], [258.0, 370.0], [249.0, 360.0]], "interior": []}}], "size": {"height": 512, "width": 512}}