{"tags": ["finished", "val"], "description": "", "objects": [{"description": "", "bitmap": null, "tags": [], "classTitle": "Agrostemma", "points": {"exterior": [[56.0, 217.0], [27.0, 227.0], [24.0, 237.0], [18.0, 239.0], [15.0, 246.0], [17.0, 265.0], [12.0, 266.0], [16.0, 300.0], [29.0, 323.0], [46.0, 339.0], [47.0, 348.0], [93.0, 324.0], [109.0, 300.0], [109.0, 280.0], [112.0, 277.0], [109.0, 258.0], [94.0, 236.0]], "interior": []}}, {"description": "", "bitmap": null, "tags": [], "classTitle": "Agrostemma", "points": {"exterior": [[511.0, 456.0], [501.0, 475.0], [487.0, 492.0], [485.0, 511.0], [511.0, 511.0]], "interior": []}}], "size": {"height": 512, "width": 512}}